pypkamd/CHARMM36mpH.ff/atomtypes.atp
pypkamd/CHARMM36mpH.ff/cmap.itp
pypkamd/CHARMM36mpH.ff/ffbonded.itp
pypkamd/CHARMM36mpH.ff/ffnonbonded.itp
pypkamd/CHARMM36mpH.ff/forcefield.doc
pypkamd/CHARMM36mpH.ff/forcefield.itp
pypkamd/CHARMM36mpH.ff/gb.itp
pypkamd/CHARMM36mpH.ff/ions.itp
pypkamd/CHARMM36mpH.ff/merged.arn
pypkamd/CHARMM36mpH.ff/merged.c.tdb
pypkamd/CHARMM36mpH.ff/merged.hdb
pypkamd/CHARMM36mpH.ff/merged.n.tdb
pypkamd/CHARMM36mpH.ff/merged.r2b
pypkamd/CHARMM36mpH.ff/merged.rtp
pypkamd/CHARMM36mpH.ff/merged.vsd
pypkamd/CHARMM36mpH.ff/merged_original.rtp.bak
pypkamd/CHARMM36mpH.ff/nbfix.itp
pypkamd/CHARMM36mpH.ff/old_c36_cmap.itp
pypkamd/CHARMM36mpH.ff/protstates.dic
pypkamd/CHARMM36mpH.ff/residuetypes.dat
pypkamd/CHARMM36mpH.ff/spc.itp
pypkamd/CHARMM36mpH.ff/spce.itp
pypkamd/CHARMM36mpH.ff/tip3p.itp
pypkamd/CHARMM36mpH.ff/tip4p.itp
pypkamd/CHARMM36mpH.ff/watermodels.dat
pypkamd/G54A7pH.ff/aminoacids.c.tdb
pypkamd/G54A7pH.ff/aminoacids.c_old.tdb
pypkamd/G54A7pH.ff/aminoacids.hdb
pypkamd/G54A7pH.ff/aminoacids.n.tdb
pypkamd/G54A7pH.ff/aminoacids.n_old.tdb
pypkamd/G54A7pH.ff/aminoacids.r2b
pypkamd/G54A7pH.ff/aminoacids.rtp
pypkamd/G54A7pH.ff/aminoacids.rtp.old
pypkamd/G54A7pH.ff/aminoacids.vsd
pypkamd/G54A7pH.ff/atomtypes.atp
pypkamd/G54A7pH.ff/dppc.itp
pypkamd/G54A7pH.ff/ff_dum.itp
pypkamd/G54A7pH.ff/ffbonded.itp
pypkamd/G54A7pH.ff/ffnonbonded.itp
pypkamd/G54A7pH.ff/forcefield.doc
pypkamd/G54A7pH.ff/forcefield.itp
pypkamd/G54A7pH.ff/ions.itp
pypkamd/G54A7pH.ff/popc.itp
pypkamd/G54A7pH.ff/protstates.dic
pypkamd/G54A7pH.ff/residuetypes.dat
pypkamd/G54A7pH.ff/spc.itp
pypkamd/G54A7pH.ff/spce.itp
pypkamd/G54A7pH.ff/tip3p.itp
pypkamd/G54A7pH.ff/tip4p.itp
pypkamd/G54A7pH.ff/tmcl.itp
pypkamd/G54A7pH.ff/watermodels.dat
pypkamd/__init__.py
pypkamd/__main__.py
pypkamd/_version.py
pypkamd/cli.py
pypkamd/configs.py
pypkamd/constants.py
pypkamd/cphmd.py
pypkamd/fixbox/fixbox
pypkamd/fixbox/fixbox.c
pypkamd/fixbox/fixbox_
pypkamd/misc.py
pypkamd/topology.py
pypkamd-0.5.1.dist-info/entry_points.txt
pypkamd-0.5.1.dist-info/WHEEL
pypkamd-0.5.1.dist-info/METADATA
pypkamd-0.5.1.dist-info/RECORD
