Metadata-Version: 2.1
Name: pypkamd
Version: 0.5.1
Summary: PypKa + GROMACS = an awesome Constant-pH Molecular Dynamics implementation
Home-page: https://github.com/mms-fcul/PypKa-MD
License: LGPLv3
Author: Pedro Reis
Author-email: pdreis@fc.ul.pt
Requires-Python: >=3.6.2,<4.0
Classifier: Development Status :: 5 - Production/Stable
Classifier: Intended Audience :: Science/Research
Classifier: License :: Other/Proprietary License
Classifier: Programming Language :: Python :: 3
Classifier: Programming Language :: Python :: 3.10
Classifier: Programming Language :: Python :: 3.7
Classifier: Programming Language :: Python :: 3.8
Classifier: Programming Language :: Python :: 3.9
Classifier: Topic :: Scientific/Engineering
Requires-Dist: pypka (==2.10.0)
Project-URL: Repository, https://github.com/mms-fcul/PypKa-MD
